<?xml version = '1.0' encoding = 'UTF-8'?>
<TableProxyOraclev20c class="oracle.dbtools.crest.model.design.storage.oracle.v20c.TableProxyOraclev20c" name="MEDIC" directorySegmentName="seg_0" id="DAAD3AC8-E27F-1020-2F49-49CC45244DD6">
<createdBy>loren</createdBy>
<createdTime>2025-02-24 00:38:42 UTC</createdTime>
<ownerDesignName>Vetfriend_Diagram</ownerDesignName>
<schemaObject>E96B5F41-403B-9BCE-825E-2272AD173FEB</schemaObject>
<logging>YES</logging>
<partitionedRowMovement>DISABLE</partitionedRowMovement>
<segment>F33F6CF2-A6DD-60A0-6C2E-D816D31A4DC9</segment>
<tableSpace>056EC95B-F61D-1C71-4985-3564268C8D4A</tableSpace>
<temporaryChanged>false</temporaryChanged>
<accessDriverType>oracle_loader</accessDriverType>
<rejectLimit></rejectLimit>
<inMemory>NO</inMemory>
<columnProxies itemClass="oracle.dbtools.crest.model.design.storage.oracle.v12c.ColumnProxyOraclev12c">
<ColumnProxy name="USERID" id="089693BB-DC30-6E1C-F8B7-728EE5E593B1">
<createdBy>loren</createdBy>
<createdTime>2025-02-24 00:38:42 UTC</createdTime>
<ownerDesignName>Vetfriend_Diagram</ownerDesignName>
</ColumnProxy>
<ColumnProxy name="SPECIALTY" id="08F9A0E5-CD82-0AC6-71F1-2C9DA16B1CCD">
<createdBy>loren</createdBy>
<createdTime>2025-02-24 00:38:42 UTC</createdTime>
<ownerDesignName>Vetfriend_Diagram</ownerDesignName>
</ColumnProxy>
<ColumnProxy name="AUDITUPDATEUSER" id="2882877D-4E72-D227-08DF-05ED0B7FF116">
<createdBy>loren</createdBy>
<createdTime>2025-02-24 00:38:42 UTC</createdTime>
<ownerDesignName>Vetfriend_Diagram</ownerDesignName>
</ColumnProxy>
<ColumnProxy name="AUDITDELETEDATE" id="344D17AB-C7D4-0A69-9EEF-7BD9FB5414AF">
<createdBy>loren</createdBy>
<createdTime>2025-02-24 00:38:42 UTC</createdTime>
<ownerDesignName>Vetfriend_Diagram</ownerDesignName>
</ColumnProxy>
<ColumnProxy name="AUDITUPDATEDATE" id="52F9DB4D-0124-5CCB-DBF6-200AB5C313F7">
<createdBy>loren</createdBy>
<createdTime>2025-02-24 00:38:42 UTC</createdTime>
<ownerDesignName>Vetfriend_Diagram</ownerDesignName>
</ColumnProxy>
<ColumnProxy name="STATE" id="5D3E8B2E-EF23-52AB-F824-3C669E1018BB">
<createdBy>loren</createdBy>
<createdTime>2025-02-24 00:38:42 UTC</createdTime>
<ownerDesignName>Vetfriend_Diagram</ownerDesignName>
</ColumnProxy>
<ColumnProxy name="AUDITCREATEDATE" id="60E22878-87C0-5949-206D-D4CE09EE4A5C">
<createdBy>loren</createdBy>
<createdTime>2025-02-24 00:38:42 UTC</createdTime>
<ownerDesignName>Vetfriend_Diagram</ownerDesignName>
</ColumnProxy>
<ColumnProxy name="AUDITCREATEUSER" id="9350F0FC-3771-ED9A-3913-6EF63437734D">
<createdBy>loren</createdBy>
<createdTime>2025-02-24 00:38:42 UTC</createdTime>
<ownerDesignName>Vetfriend_Diagram</ownerDesignName>
</ColumnProxy>
<ColumnProxy name="MEDICID" id="A072E1E7-C308-2BCF-6104-704374240C36">
<createdBy>loren</createdBy>
<createdTime>2025-02-24 00:38:42 UTC</createdTime>
<ownerDesignName>Vetfriend_Diagram</ownerDesignName>
<autoIncrementDDL>IDENTITY_CLAUSE</autoIncrementDDL>
</ColumnProxy>
<ColumnProxy name="AUDITDELETEUSER" id="FD8F19E0-B23C-E755-2DE7-A3822CC3E06C">
<createdBy>loren</createdBy>
<createdTime>2025-02-24 00:38:42 UTC</createdTime>
<ownerDesignName>Vetfriend_Diagram</ownerDesignName>
</ColumnProxy>
<ColumnProxy name="PHONE" id="FF30E883-5E71-9337-0A39-B3FBD9698C27">
<createdBy>loren</createdBy>
<createdTime>2025-02-24 00:38:42 UTC</createdTime>
<ownerDesignName>Vetfriend_Diagram</ownerDesignName>
</ColumnProxy>
</columnProxies>
<indexProxies>
<IndexProxy class="oracle.dbtools.crest.model.design.storage.oracle.v10g.IndexProxyOraclev10g" name="IDX_MEDIC_USERID" id="15A1CA16-92B3-AA46-AA90-F24D539D8CB9">
<createdBy>loren</createdBy>
<createdTime>2025-02-24 00:38:42 UTC</createdTime>
<ownerDesignName>Vetfriend_Diagram</ownerDesignName>
<schemaObject>E96B5F41-403B-9BCE-825E-2272AD173FEB</schemaObject>
<segment>2BA7A593-9A87-DB6D-B44E-BD10954A53FF</segment>
<tableSpace>056EC95B-F61D-1C71-4985-3564268C8D4A</tableSpace>
</IndexProxy>
</indexProxies>
<foreignKeys>
<ForeignKey class="oracle.dbtools.crest.model.design.storage.oracle.v10g.FKProxyOraclev10g" name="FK_MEDIC_USER" id="870213F4-659A-9D59-5C88-1375ACF2BB9A">
<createdBy>loren</createdBy>
<createdTime>2025-02-24 00:38:43 UTC</createdTime>
<ownerDesignName>Vetfriend_Diagram</ownerDesignName>
</ForeignKey>
</foreignKeys>
<primaryKeys>
<PrimaryKey class="oracle.dbtools.crest.model.design.storage.oracle.v10g.PKProxyOraclev10g" name="MEDIC_PK" id="195AF0EB-1824-6D1C-6C77-FB8C858DE597">
<createdBy>loren</createdBy>
<createdTime>2025-02-24 00:38:43 UTC</createdTime>
<ownerDesignName>Vetfriend_Diagram</ownerDesignName>
<schemaObject>E96B5F41-403B-9BCE-825E-2272AD173FEB</schemaObject>
<segment>2BA7A593-9A87-DB6D-B44E-BD10954A53FF</segment>
<tableSpace>056EC95B-F61D-1C71-4985-3564268C8D4A</tableSpace>
<indexSegment>2BA7A593-9A87-DB6D-B44E-BD10954A53FF</indexSegment>
<indexSort>SORTED</indexSort>
<usingIndex>BY INDEX NAME</usingIndex>
</PrimaryKey>
</primaryKeys>
</TableProxyOraclev20c>